cge_comrare_pipeline/Helpers.py
cge_comrare_pipeline/PCA.py
cge_comrare_pipeline/SampleQC.py
cge_comrare_pipeline/VariantQC.py
cge_comrare_pipeline/__init__.py
cge_comrare_pipeline/__main__.py
cge_comrare_pipeline-0.1.0.dist-info/METADATA
cge_comrare_pipeline-0.1.0.dist-info/WHEEL
cge_comrare_pipeline-0.1.0.dist-info/RECORD
