Metadata-Version: 2.1
Name: cge-comrare-pipeline
Version: 0.1.0
Summary: package to run a genotype quality control pipeline
Author: Luis Giraldo González
Author-email: luisggon@protonmail.com
Requires-Python: >=3.11,<4.0
Classifier: License :: OSI Approved :: MIT License
Classifier: Operating System :: OS Independent
Classifier: Programming Language :: Python :: 3
Classifier: Programming Language :: Python :: 3.11
Classifier: Programming Language :: Python :: 3.12
Requires-Dist: matplotlib (>=3.8.3,<4.0.0)
Requires-Dist: pandas (>=2.2.1,<3.0.0)
Requires-Dist: requests (>=2.31.0,<3.0.0)
Requires-Dist: scipy (>=1.12.0,<2.0.0)
Requires-Dist: seaborn (>=0.13.2,<0.14.0)
